[
  {
    "title": "30代後半になって初めて発信活動を始めたら人生が変わった話",
    "url": "https://qiita.com/kojimadev/items/f4a6539e4fbc641c6fa0",
    "likes_count": 1192,
    "created_at": "2022-03-08T07:47:09+09:00",
    "updated_at": "2022-03-23T11:36:27+09:00",
    "id": "kojimadev"
  },
  {
    "title": "コードレビューで嫌われる人の特徴7選",
    "url": "https://qiita.com/emjo1804/items/48f6e78237a04684ab38",
    "likes_count": 1156,
    "created_at": "2022-03-16T06:01:32+09:00",
    "updated_at": "2022-03-24T23:33:26+09:00",
    "id": "emjo1804"
  },
  {
    "title": "機械学習エンジニアに爆速でなるための教材集",
    "url": "https://qiita.com/KangsooKim/items/8d987a7089297068477b",
    "likes_count": 477,
    "created_at": "2022-03-06T22:33:26+09:00",
    "updated_at": "2022-03-06T22:33:26+09:00",
    "id": "KangsooKim"
  },
  {
    "title": "[C#]最新言語仕様を使った『宣言的プログラミング』でバグが少なく可読性の高い高品質なコードを書こう",
    "url": "https://qiita.com/jun1s/items/5f60bbb886626d897abc",
    "likes_count": 452,
    "created_at": "2022-03-02T07:02:36+09:00",
    "updated_at": "2022-03-28T08:39:03+09:00",
    "id": "jun1s"
  },
  {
    "title": "仕事が暇な時にすることリスト",
    "url": "https://qiita.com/mitsuhiro_K/items/2439b05deeca5b148f49",
    "likes_count": 385,
    "created_at": "2022-03-08T20:29:47+09:00",
    "updated_at": "2022-03-08T20:29:47+09:00",
    "id": "mitsuhiro_K"
  },
  {
    "title": "AWS公式が提供する無料ゲームでAWSについて学べるらしい",
    "url": "https://qiita.com/tak001/items/f4c7ff6db862e3d283e3",
    "likes_count": 374,
    "created_at": "2022-03-20T10:41:50+09:00",
    "updated_at": "2022-03-23T14:26:24+09:00",
    "id": "tak001"
  },
  {
    "title": "きれいなPythonプログラミング（パイソニックなコードを書こう）を読んでみた",
    "url": "https://qiita.com/inetcpl/items/af42b8221d9447637449",
    "likes_count": 352,
    "created_at": "2022-03-16T22:43:40+09:00",
    "updated_at": "2022-03-19T10:57:31+09:00",
    "id": "inetcpl"
  },
  {
    "title": "利用者は数十億人！？ SQLiteはどこが凄いデータベース管理システムなのか調べてみた",
    "url": "https://qiita.com/ko1nksm/items/87d27a287e1b6005d11c",
    "likes_count": 347,
    "created_at": "2022-03-06T23:12:07+09:00",
    "updated_at": "2022-03-09T22:44:38+09:00",
    "id": "ko1nksm"
  }
]
